LICENSE
MANIFEST.in
README.md
setup.py
pygrisb/__init__.py
pygrisb/__init__.pyc
pygrisb.egg-info/PKG-INFO
pygrisb.egg-info/SOURCES.txt
pygrisb.egg-info/dependency_links.txt
pygrisb.egg-info/requires.txt
pygrisb.egg-info/top_level.txt
pygrisb/__pycache__/__init__.cpython-37.pyc
pygrisb/basic/__init__.py
pygrisb/basic/__init__.pyc
pygrisb/basic/data.py
pygrisb/basic/prints.py
pygrisb/basic/prints.pyc
pygrisb/basic/splot.py
pygrisb/basic/units.py
pygrisb/basic/units.pyc
pygrisb/basic/__pycache__/__init__.cpython-37.pyc
pygrisb/basic/__pycache__/data.cpython-37.pyc
pygrisb/basic/__pycache__/prints.cpython-37.pyc
pygrisb/basic/__pycache__/splot.cpython-37.pyc
pygrisb/basic/__pycache__/units.cpython-37.pyc
pygrisb/compatible/__init__.py
pygrisb/compatible/__init__.pyc
pygrisb/compatible/fio.py
pygrisb/compatible/__pycache__/__init__.cpython-37.pyc
pygrisb/dft/__init__.py
pygrisb/dft/__init__.pyc
pygrisb/dft/eos.py
pygrisb/dft/wien.py
pygrisb/dft/__pycache__/__init__.cpython-37.pyc
pygrisb/dft/__pycache__/wien.cpython-37.pyc
pygrisb/estructure/__init__.py
pygrisb/estructure/__init__.pyc
pygrisb/estructure/bandstruct.py
pygrisb/estructure/bandstruct.pyc
pygrisb/estructure/bz.py
pygrisb/estructure/dos.py
pygrisb/estructure/dos.pyc
pygrisb/estructure/fermi.py
pygrisb/estructure/gwannier.py
pygrisb/estructure/__pycache__/__init__.cpython-37.pyc
pygrisb/estructure/__pycache__/bandstruct.cpython-37.pyc
pygrisb/estructure/__pycache__/dos.cpython-37.pyc
pygrisb/estructure/misc/dos_nch.py
pygrisb/estructure/misc/fermi.py
pygrisb/gsolver/__init__.py
pygrisb/gsolver/__init__.pyc
pygrisb/gsolver/gs_c2rspci_mott_onfly.py
pygrisb/gsolver/gs_ed.py
pygrisb/gsolver/gs_idmrg.py
pygrisb/gsolver/gs_qc.py
pygrisb/gsolver/gs_ridmrg.py
pygrisb/gsolver/gs_syten.py
pygrisb/gsolver/gsolver.py
pygrisb/gsolver/__pycache__/__init__.cpython-37.pyc
pygrisb/gutz/__init__.py
pygrisb/gutz/__init__.pyc
pygrisb/gutz/atoms.py
pygrisb/gutz/batch_init.py
pygrisb/gutz/embedh.py
pygrisb/gutz/gatom.py
pygrisb/gutz/getwiencase.py
pygrisb/gutz/ginput.py
pygrisb/gutz/init.py
pygrisb/gutz/init_magnet_conf.py
pygrisb/gutz/init_mott.py
