Metadata-Version: 1.1
Name: pygrisb
Version: 2019.3.18.1
Summary: Python libraries for CyGutz package
Home-page: https://gitlab.com/yxphysics/pygrisb
Author: Yongxin Yao, Nicola Lanata, Xiaoyu Deng
Author-email: cygutz@gmail.com
License: GPL
Platform: UNKNOWN
Classifier: Development Status :: 3 - Alpha
Classifier: Intended Audience :: Developers
Classifier: Topic :: Software Development :: Build Tools
Classifier: License :: OSI Approved :: GNU Lesser General Public License v3 or later (LGPLv3+)
Classifier: Programming Language :: Python :: 3.7
